zfdb/__init__.py
zfdb/core.py
zfdb-0.1.1.dist-info/LICENSE
zfdb-0.1.1.dist-info/METADATA
zfdb-0.1.1.dist-info/WHEEL
zfdb-0.1.1.dist-info/RECORD
