Metadata-Version: 2.1
Name: zfdb
Version: 0.1.1
Summary: Simple interface to the ZIP files to use them as a database
Home-page: https://github.com/semolex/zfdb
License: MIT
Keywords: db,key-value,zip,python,database,filesystem,file,storage,zipfile-database,zipfile-db,zip-db,zip-database,zipfile-storage,zip-storage
Author: Oleksii
Author-email: semolex@live.com
Requires-Python: >=3.9,<4.0
Classifier: Development Status :: 5 - Production/Stable
Classifier: Intended Audience :: Developers
Classifier: License :: OSI Approved :: MIT License
Classifier: Natural Language :: English
Classifier: Operating System :: OS Independent
Classifier: Programming Language :: Python :: 3
Classifier: Programming Language :: Python :: 3.9
Classifier: Programming Language :: Python :: 3.10
Classifier: Programming Language :: Python :: 3.11
Classifier: Programming Language :: Python :: 3.12
Classifier: Programming Language :: Python :: 3 :: Only
Classifier: Programming Language :: Python :: Implementation :: CPython
Classifier: Topic :: Database
Classifier: Topic :: Database :: Database Engines/Servers
Classifier: Topic :: Software Development :: Libraries :: Python Modules
Classifier: Topic :: System :: Archiving
Classifier: Topic :: System :: Filesystems
Classifier: Typing :: Typed
Project-URL: Repository, https://github.com/semolex/zfdb
